MANIFEST.in
README.rst
setup.py
Adafruit_Thermal/Adafruit_Thermal.py
Adafruit_Thermal/__init__.py
Adafruit_Thermal.egg-info/PKG-INFO
Adafruit_Thermal.egg-info/SOURCES.txt
Adafruit_Thermal.egg-info/dependency_links.txt
Adafruit_Thermal.egg-info/not-zip-safe
Adafruit_Thermal.egg-info/requires.txt
Adafruit_Thermal.egg-info/top_level.txt