Metadata-Version: 1.1
Name: Adafruit-Thermal
Version: 1.1.0
Summary: Library for controlling Adafruit Thermal Printers
Home-page: https://github.com/bareo/Python-Thermal-Printer
Author: zach wick
Author-email: zwick@bareo.io
License: MIT
Keywords: adafruit thermal printer serial
Platform: UNKNOWN
Classifier: License :: OSI Approved :: MIT License
Classifier: Intended Audience :: Developers
Classifier: Programming Language :: Python :: 3.4
Classifier: Programming Language :: Python :: 2.7
